merge_mate/__init__.py
merge_mate/main.py
merge_mate/merge_mate.py
merge_mate/merge_mate_tui.py
merge_mate/resolver.py
merge_mate_ai-1.0.1.dist-info/licenses/LICENSE
merge_mate_ai-1.0.1.dist-info/METADATA
merge_mate_ai-1.0.1.dist-info/WHEEL
merge_mate_ai-1.0.1.dist-info/entry_points.txt
merge_mate_ai-1.0.1.dist-info/top_level.txt
merge_mate_ai-1.0.1.dist-info/RECORD
